sdtp/__init__.py
sdtp/sdtp_client.py
sdtp/sdtp_filter.py
sdtp/sdtp_schema.py
sdtp/sdtp_server.py
sdtp/sdtp_table.py
sdtp/sdtp_table_factory.py
sdtp/sdtp_utils.py
sdtp/table_server.py
sdtp-2026.1.18.dist-info/licenses/AUTHORS.rst
sdtp-2026.1.18.dist-info/licenses/LICENSE
sdtp-2026.1.18.dist-info/METADATA
sdtp-2026.1.18.dist-info/WHEEL
sdtp-2026.1.18.dist-info/top_level.txt
sdtp-2026.1.18.dist-info/RECORD
