Metadata-Version: 2.4
Name: sdtp
Version: 2026.1.18
Summary: Simple Data Transfer Protocol (SDTP) reference implementation
Author-email: The Regents of the University of California <opensource@ucop.edu>
License-Expression: BSD-3-Clause
Project-URL: Homepage, https://global-data-plane.github.io/sdtp/
Project-URL: Documentation, https://global-data-plane.github.io/sdtp/
Project-URL: Source, https://github.com/Global-Data-Plane/sdtp
Requires-Python: >=3.8
License-File: LICENSE
License-File: AUTHORS.rst
Requires-Dist: flask
Requires-Dist: pandas
Requires-Dist: pydantic
Requires-Dist: requests
Requires-Dist: pyyaml
Provides-Extra: gcs
Requires-Dist: google-cloud-storage; extra == "gcs"
Requires-Dist: google-cloud-core; extra == "gcs"
Dynamic: license-file
